{
  "info": {
    "_postman_id": "8a123456-2efe-4b1f-aad8-tasks-backend",
    "name": "Collaboration Platform - Work Management",
    "description": "Postman collection for testing Work Management plus task-scoped Collaboration endpoints. Requires an authenticated session from the Identity + Projects setup.",
    "schema": "https://schema.getpostman.com/json/collection/v2.1.0/collection.json"
  },
  "variable": [
    {
      "key": "baseUrl",
      "value": "http://localhost:8080",
      "type": "string"
    },
    {
      "key": "projectRef",
      "value": "",
      "type": "string"
    },
    {
      "key": "teamRef",
      "value": "",
      "type": "string"
    },
    {
      "key": "taskId",
      "value": "",
      "type": "string"
    },
    {
      "key": "subTaskId",
      "value": "",
      "type": "string"
    },
    {
      "key": "labelId",
      "value": "",
      "type": "string"
    },
    {
      "key": "commentId",
      "value": "",
      "type": "string"
    },
    {
      "key": "attachmentId",
      "value": "",
      "type": "string"
    },
    {
      "key": "timeEntryId",
      "value": "",
      "type": "string"
    }
  ],
  "item": [
    {
      "name": "Labels",
      "item": [
        {
          "name": "Create Label",
          "event": [
            {
              "listen": "test",
              "script": {
                "exec": [
                  "if (pm.response.code === 201) {",
                  "  const body = pm.response.json();",
                  "  pm.collectionVariables.set('labelId', body.id);",
                  "}"
                ],
                "type": "text/javascript"
              }
            }
          ],
          "request": {
            "method": "POST",
            "header": [
              { "key": "Content-Type", "value": "application/json" }
            ],
            "body": {
              "mode": "raw",
              "raw": "{\n  \"name\": \"bug\",\n  \"color\": \"#FF5733\"\n}"
            },
            "url": {
              "raw": "{{baseUrl}}/api/projects/{{projectRef}}/labels",
              "host": ["{{baseUrl}}"],
              "path": ["api", "projects", "{{projectRef}}", "labels"]
            },
            "description": "Creates a label scoped to a project. Requires contributor role."
          }
        },
        {
          "name": "Create Label - Enhancement",
          "event": [
            {
              "listen": "test",
              "script": {
                "exec": [
                  "if (pm.response.code === 201) {",
                  "  const body = pm.response.json();",
                  "  pm.collectionVariables.set('labelId', body.id);",
                  "}"
                ],
                "type": "text/javascript"
              }
            }
          ],
          "request": {
            "method": "POST",
            "header": [
              { "key": "Content-Type", "value": "application/json" }
            ],
            "body": {
              "mode": "raw",
              "raw": "{\n  \"name\": \"enhancement\",\n  \"color\": \"#33FF57\"\n}"
            },
            "url": {
              "raw": "{{baseUrl}}/api/projects/{{projectRef}}/labels",
              "host": ["{{baseUrl}}"],
              "path": ["api", "projects", "{{projectRef}}", "labels"]
            },
            "description": "Creates a second label for testing multi-label assignment."
          }
        },
        {
          "name": "List Labels",
          "request": {
            "method": "GET",
            "header": [],
            "url": {
              "raw": "{{baseUrl}}/api/projects/{{projectRef}}/labels",
              "host": ["{{baseUrl}}"],
              "path": ["api", "projects", "{{projectRef}}", "labels"]
            },
            "description": "Lists all labels for a project."
          }
        },
        {
          "name": "Delete Label",
          "request": {
            "method": "DELETE",
            "header": [],
            "url": {
              "raw": "{{baseUrl}}/api/projects/{{projectRef}}/labels/{{labelId}}",
              "host": ["{{baseUrl}}"],
              "path": ["api", "projects", "{{projectRef}}", "labels", "{{labelId}}"]
            },
            "description": "Deletes a label. Requires manager role."
          }
        }
      ]
    },
    {
      "name": "Tasks",
      "item": [
        {
          "name": "Create Task",
          "event": [
            {
              "listen": "test",
              "script": {
                "exec": [
                  "if (pm.response.code === 201) {",
                  "  const body = pm.response.json();",
                  "  pm.collectionVariables.set('taskId', body.id);",
                  "}"
                ],
                "type": "text/javascript"
              }
            }
          ],
          "request": {
            "method": "POST",
            "header": [
              { "key": "Content-Type", "value": "application/json" }
            ],
            "body": {
              "mode": "raw",
              "raw": "{\n  \"title\": \"Implement login page\",\n  \"description\": \"Build the login UI with email/password fields and validation\",\n  \"priority\": \"HIGH\",\n  \"dueDate\": \"2026-07-01\"\n}"
            },
            "url": {
              "raw": "{{baseUrl}}/api/projects/{{projectRef}}/teams/{{teamRef}}/tasks",
              "host": ["{{baseUrl}}"],
              "path": ["api", "projects", "{{projectRef}}", "teams", "{{teamRef}}", "tasks"]
            },
            "description": "Creates a task in a team. Requires contributor role."
          }
        },
        {
          "name": "Create Task - Medium Priority",
          "event": [
            {
              "listen": "test",
              "script": {
                "exec": [
                  "if (pm.response.code === 201) {",
                  "  const body = pm.response.json();",
                  "  pm.collectionVariables.set('taskId', body.id);",
                  "}"
                ],
                "type": "text/javascript"
              }
            }
          ],
          "request": {
            "method": "POST",
            "header": [
              { "key": "Content-Type", "value": "application/json" }
            ],
            "body": {
              "mode": "raw",
              "raw": "{\n  \"title\": \"Add dark mode toggle\",\n  \"description\": \"Implement a theme switcher between light and dark mode\",\n  \"priority\": \"MEDIUM\",\n  \"dueDate\": \"2026-07-15\"\n}"
            },
            "url": {
              "raw": "{{baseUrl}}/api/projects/{{projectRef}}/teams/{{teamRef}}/tasks",
              "host": ["{{baseUrl}}"],
              "path": ["api", "projects", "{{projectRef}}", "teams", "{{teamRef}}", "tasks"]
            },
            "description": "Creates a second task for testing pagination and listing."
          }
        },
        {
          "name": "List Tasks",
          "request": {
            "method": "GET",
            "header": [],
            "url": {
              "raw": "{{baseUrl}}/api/projects/{{projectRef}}/teams/{{teamRef}}/tasks?page=1&size=10",
              "host": ["{{baseUrl}}"],
              "path": ["api", "projects", "{{projectRef}}", "teams", "{{teamRef}}", "tasks"],
              "query": [
                { "key": "page", "value": "1" },
                { "key": "size", "value": "10" }
              ]
            },
            "description": "Lists tasks in a team with pagination."
          }
        },
        {
          "name": "Get Task",
          "request": {
            "method": "GET",
            "header": [],
            "url": {
              "raw": "{{baseUrl}}/api/projects/{{projectRef}}/teams/{{teamRef}}/tasks/{{taskId}}",
              "host": ["{{baseUrl}}"],
              "path": ["api", "projects", "{{projectRef}}", "teams", "{{teamRef}}", "tasks", "{{taskId}}"]
            },
            "description": "Gets a single task by ID."
          }
        },
        {
          "name": "Update Task",
          "request": {
            "method": "PATCH",
            "header": [
              { "key": "Content-Type", "value": "application/json" }
            ],
            "body": {
              "mode": "raw",
              "raw": "{\n  \"title\": \"Implement login page with SSO\",\n  \"priority\": \"URGENT\"\n}"
            },
            "url": {
              "raw": "{{baseUrl}}/api/projects/{{projectRef}}/teams/{{teamRef}}/tasks/{{taskId}}",
              "host": ["{{baseUrl}}"],
              "path": ["api", "projects", "{{projectRef}}", "teams", "{{teamRef}}", "tasks", "{{taskId}}"]
            },
            "description": "Updates task title and/or priority. Requires contributor role."
          }
        },
        {
          "name": "Update Task Status",
          "request": {
            "method": "PATCH",
            "header": [
              { "key": "Content-Type", "value": "application/json" }
            ],
            "body": {
              "mode": "raw",
              "raw": "{\n  \"status\": \"IN_PROGRESS\"\n}"
            },
            "url": {
              "raw": "{{baseUrl}}/api/projects/{{projectRef}}/teams/{{teamRef}}/tasks/{{taskId}}/status",
              "host": ["{{baseUrl}}"],
              "path": ["api", "projects", "{{projectRef}}", "teams", "{{teamRef}}", "tasks", "{{taskId}}", "status"]
            },
            "description": "Updates the task status. Valid values: TODO, IN_PROGRESS, IN_REVIEW, DONE."
          }
        },
        {
          "name": "Delete Task",
          "request": {
            "method": "DELETE",
            "header": [],
            "url": {
              "raw": "{{baseUrl}}/api/projects/{{projectRef}}/teams/{{teamRef}}/tasks/{{taskId}}",
              "host": ["{{baseUrl}}"],
              "path": ["api", "projects", "{{projectRef}}", "teams", "{{teamRef}}", "tasks", "{{taskId}}"]
            },
            "description": "Deletes a task. Work-owned rows are deleted directly; collaboration rows are cleaned by the Collaboration module through TaskDeletedEvent. Requires manager role."
          }
        }
      ]
    },
    {
      "name": "Sub-Tasks",
      "item": [
        {
          "name": "Create Sub-Task",
          "event": [
            {
              "listen": "test",
              "script": {
                "exec": [
                  "if (pm.response.code === 201) {",
                  "  const body = pm.response.json();",
                  "  pm.collectionVariables.set('subTaskId', body.id);",
                  "}"
                ],
                "type": "text/javascript"
              }
            }
          ],
          "request": {
            "method": "POST",
            "header": [
              { "key": "Content-Type", "value": "application/json" }
            ],
            "body": {
              "mode": "raw",
              "raw": "{\n  \"title\": \"Design login form layout\"\n}"
            },
            "url": {
              "raw": "{{baseUrl}}/api/projects/{{projectRef}}/teams/{{teamRef}}/tasks/{{taskId}}/subtasks",
              "host": ["{{baseUrl}}"],
              "path": ["api", "projects", "{{projectRef}}", "teams", "{{teamRef}}", "tasks", "{{taskId}}", "subtasks"]
            },
            "description": "Creates a sub-task for the current task."
          }
        },
        {
          "name": "Create Sub-Task 2",
          "event": [
            {
              "listen": "test",
              "script": {
                "exec": [
                  "if (pm.response.code === 201) {",
                  "  const body = pm.response.json();",
                  "  pm.collectionVariables.set('subTaskId', body.id);",
                  "}"
                ],
                "type": "text/javascript"
              }
            }
          ],
          "request": {
            "method": "POST",
            "header": [
              { "key": "Content-Type", "value": "application/json" }
            ],
            "body": {
              "mode": "raw",
              "raw": "{\n  \"title\": \"Add form validation\"\n}"
            },
            "url": {
              "raw": "{{baseUrl}}/api/projects/{{projectRef}}/teams/{{teamRef}}/tasks/{{taskId}}/subtasks",
              "host": ["{{baseUrl}}"],
              "path": ["api", "projects", "{{projectRef}}", "teams", "{{teamRef}}", "tasks", "{{taskId}}", "subtasks"]
            },
            "description": "Creates a second sub-task."
          }
        },
        {
          "name": "List Sub-Tasks",
          "request": {
            "method": "GET",
            "header": [],
            "url": {
              "raw": "{{baseUrl}}/api/projects/{{projectRef}}/teams/{{teamRef}}/tasks/{{taskId}}/subtasks",
              "host": ["{{baseUrl}}"],
              "path": ["api", "projects", "{{projectRef}}", "teams", "{{teamRef}}", "tasks", "{{taskId}}", "subtasks"]
            },
            "description": "Lists all sub-tasks for a task."
          }
        },
        {
          "name": "Complete Sub-Task",
          "request": {
            "method": "PATCH",
            "header": [
              { "key": "Content-Type", "value": "application/json" }
            ],
            "body": {
              "mode": "raw",
              "raw": "{\n  \"isDone\": true\n}"
            },
            "url": {
              "raw": "{{baseUrl}}/api/projects/{{projectRef}}/teams/{{teamRef}}/tasks/{{taskId}}/subtasks/{{subTaskId}}",
              "host": ["{{baseUrl}}"],
              "path": ["api", "projects", "{{projectRef}}", "teams", "{{teamRef}}", "tasks", "{{taskId}}", "subtasks", "{{subTaskId}}"]
            },
            "description": "Marks a sub-task as done."
          }
        },
        {
          "name": "Reopen Sub-Task",
          "request": {
            "method": "PATCH",
            "header": [
              { "key": "Content-Type", "value": "application/json" }
            ],
            "body": {
              "mode": "raw",
              "raw": "{\n  \"isDone\": false\n}"
            },
            "url": {
              "raw": "{{baseUrl}}/api/projects/{{projectRef}}/teams/{{teamRef}}/tasks/{{taskId}}/subtasks/{{subTaskId}}",
              "host": ["{{baseUrl}}"],
              "path": ["api", "projects", "{{projectRef}}", "teams", "{{teamRef}}", "tasks", "{{taskId}}", "subtasks", "{{subTaskId}}"]
            },
            "description": "Re-opens a completed sub-task."
          }
        },
        {
          "name": "Delete Sub-Task",
          "request": {
            "method": "DELETE",
            "header": [],
            "url": {
              "raw": "{{baseUrl}}/api/projects/{{projectRef}}/teams/{{teamRef}}/tasks/{{taskId}}/subtasks/{{subTaskId}}",
              "host": ["{{baseUrl}}"],
              "path": ["api", "projects", "{{projectRef}}", "teams", "{{teamRef}}", "tasks", "{{taskId}}", "subtasks", "{{subTaskId}}"]
            },
            "description": "Deletes a sub-task."
          }
        }
      ]
    },
    {
      "name": "Collaboration - Comments",
      "item": [
        {
          "name": "Create Comment",
          "event": [
            {
              "listen": "test",
              "script": {
                "exec": [
                  "if (pm.response.code === 201) {",
                  "  const body = pm.response.json();",
                  "  pm.collectionVariables.set('commentId', body.id);",
                  "}"
                ],
                "type": "text/javascript"
              }
            }
          ],
          "request": {
            "method": "POST",
            "header": [
              { "key": "Content-Type", "value": "application/json" }
            ],
            "body": {
              "mode": "raw",
              "raw": "{\n  \"content\": \"I think we should use a clean minimalist design for the login page.\"\n}"
            },
            "url": {
              "raw": "{{baseUrl}}/api/projects/{{projectRef}}/teams/{{teamRef}}/tasks/{{taskId}}/comments",
              "host": ["{{baseUrl}}"],
              "path": ["api", "projects", "{{projectRef}}", "teams", "{{teamRef}}", "tasks", "{{taskId}}", "comments"]
            },
            "description": "Adds a task comment through the Collaboration module."
          }
        },
        {
          "name": "Create Comment 2",
          "event": [
            {
              "listen": "test",
              "script": {
                "exec": [
                  "if (pm.response.code === 201) {",
                  "  const body = pm.response.json();",
                  "  pm.collectionVariables.set('commentId', body.id);",
                  "}"
                ],
                "type": "text/javascript"
              }
            }
          ],
          "request": {
            "method": "POST",
            "header": [
              { "key": "Content-Type", "value": "application/json" }
            ],
            "body": {
              "mode": "raw",
              "raw": "{\n  \"content\": \"Don't forget to add input validation and error states.\"\n}"
            },
            "url": {
              "raw": "{{baseUrl}}/api/projects/{{projectRef}}/teams/{{teamRef}}/tasks/{{taskId}}/comments",
              "host": ["{{baseUrl}}"],
              "path": ["api", "projects", "{{projectRef}}", "teams", "{{teamRef}}", "tasks", "{{taskId}}", "comments"]
            },
            "description": "Adds a second task comment through the Collaboration module."
          }
        },
        {
          "name": "List Comments",
          "request": {
            "method": "GET",
            "header": [],
            "url": {
              "raw": "{{baseUrl}}/api/projects/{{projectRef}}/teams/{{teamRef}}/tasks/{{taskId}}/comments?page=1&size=10",
              "host": ["{{baseUrl}}"],
              "path": ["api", "projects", "{{projectRef}}", "teams", "{{teamRef}}", "tasks", "{{taskId}}", "comments"],
              "query": [
                { "key": "page", "value": "1" },
                { "key": "size", "value": "10" }
              ]
            },
            "description": "Lists task comments from the Collaboration module with pagination (newest first)."
          }
        },
        {
          "name": "Delete Comment",
          "request": {
            "method": "DELETE",
            "header": [],
            "url": {
              "raw": "{{baseUrl}}/api/projects/{{projectRef}}/teams/{{teamRef}}/tasks/{{taskId}}/comments/{{commentId}}",
              "host": ["{{baseUrl}}"],
              "path": ["api", "projects", "{{projectRef}}", "teams", "{{teamRef}}", "tasks", "{{taskId}}", "comments", "{{commentId}}"]
            },
            "description": "Deletes a task comment. Only the comment author can delete their own comments."
          }
        }
      ]
    },
    {
      "name": "Collaboration - Attachments",
      "item": [
        {
          "name": "Add Attachment",
          "event": [
            {
              "listen": "test",
              "script": {
                "exec": [
                  "if (pm.response.code === 201) {",
                  "  const body = pm.response.json();",
                  "  pm.collectionVariables.set('attachmentId', body.id);",
                  "}"
                ],
                "type": "text/javascript"
              }
            }
          ],
          "request": {
            "method": "POST",
            "header": [
              { "key": "Content-Type", "value": "application/json" }
            ],
            "body": {
              "mode": "raw",
              "raw": "{\n  \"fileName\": \"screenshot.png\",\n  \"fileUrl\": \"https://storage.example.com/tasks/screenshot.png\",\n  \"fileSize\": 2048576\n}"
            },
            "url": {
              "raw": "{{baseUrl}}/api/projects/{{projectRef}}/teams/{{teamRef}}/tasks/{{taskId}}/attachments",
              "host": ["{{baseUrl}}"],
              "path": ["api", "projects", "{{projectRef}}", "teams", "{{teamRef}}", "tasks", "{{taskId}}", "attachments"]
            },
            "description": "Registers a task attachment through the Collaboration module."
          }
        },
        {
          "name": "List Attachments",
          "request": {
            "method": "GET",
            "header": [],
            "url": {
              "raw": "{{baseUrl}}/api/projects/{{projectRef}}/teams/{{teamRef}}/tasks/{{taskId}}/attachments",
              "host": ["{{baseUrl}}"],
              "path": ["api", "projects", "{{projectRef}}", "teams", "{{teamRef}}", "tasks", "{{taskId}}", "attachments"]
            },
            "description": "Lists all task attachments from the Collaboration module (newest first)."
          }
        },
        {
          "name": "Delete Attachment",
          "request": {
            "method": "DELETE",
            "header": [],
            "url": {
              "raw": "{{baseUrl}}/api/projects/{{projectRef}}/teams/{{teamRef}}/tasks/{{taskId}}/attachments/{{attachmentId}}",
              "host": ["{{baseUrl}}"],
              "path": ["api", "projects", "{{projectRef}}", "teams", "{{teamRef}}", "tasks", "{{taskId}}", "attachments", "{{attachmentId}}"]
            },
            "description": "Deletes a task attachment. Only the uploader can delete their own attachments."
          }
        }
      ]
    },
    {
      "name": "Time Entries",
      "item": [
        {
          "name": "Log Time",
          "event": [
            {
              "listen": "test",
              "script": {
                "exec": [
                  "if (pm.response.code === 201) {",
                  "  const body = pm.response.json();",
                  "  pm.collectionVariables.set('timeEntryId', body.id);",
                  "}"
                ],
                "type": "text/javascript"
              }
            }
          ],
          "request": {
            "method": "POST",
            "header": [
              { "key": "Content-Type", "value": "application/json" }
            ],
            "body": {
              "mode": "raw",
              "raw": "{\n  \"durationMinutes\": 120,\n  \"date\": \"2026-06-11\",\n  \"description\": \"Worked on login form layout and validation\"\n}"
            },
            "url": {
              "raw": "{{baseUrl}}/api/projects/{{projectRef}}/teams/{{teamRef}}/tasks/{{taskId}}/time-entries",
              "host": ["{{baseUrl}}"],
              "path": ["api", "projects", "{{projectRef}}", "teams", "{{teamRef}}", "tasks", "{{taskId}}", "time-entries"]
            },
            "description": "Logs time spent on a task."
          }
        },
        {
          "name": "Log Time 2",
          "event": [
            {
              "listen": "test",
              "script": {
                "exec": [
                  "if (pm.response.code === 201) {",
                  "  const body = pm.response.json();",
                  "  pm.collectionVariables.set('timeEntryId', body.id);",
                  "}"
                ],
                "type": "text/javascript"
              }
            }
          ],
          "request": {
            "method": "POST",
            "header": [
              { "key": "Content-Type", "value": "application/json" }
            ],
            "body": {
              "mode": "raw",
              "raw": "{\n  \"durationMinutes\": 60,\n  \"date\": \"2026-06-12\",\n  \"description\": \"Code review and testing\"\n}"
            },
            "url": {
              "raw": "{{baseUrl}}/api/projects/{{projectRef}}/teams/{{teamRef}}/tasks/{{taskId}}/time-entries",
              "host": ["{{baseUrl}}"],
              "path": ["api", "projects", "{{projectRef}}", "teams", "{{teamRef}}", "tasks", "{{taskId}}", "time-entries"]
            },
            "description": "Logs another time entry."
          }
        },
        {
          "name": "List Time Entries",
          "request": {
            "method": "GET",
            "header": [],
            "url": {
              "raw": "{{baseUrl}}/api/projects/{{projectRef}}/teams/{{teamRef}}/tasks/{{taskId}}/time-entries?page=1&size=10",
              "host": ["{{baseUrl}}"],
              "path": ["api", "projects", "{{projectRef}}", "teams", "{{teamRef}}", "tasks", "{{taskId}}", "time-entries"],
              "query": [
                { "key": "page", "value": "1" },
                { "key": "size", "value": "10" }
              ]
            },
            "description": "Lists time entries for a task with pagination (newest first)."
          }
        },
        {
          "name": "Delete Time Entry",
          "request": {
            "method": "DELETE",
            "header": [],
            "url": {
              "raw": "{{baseUrl}}/api/projects/{{projectRef}}/teams/{{teamRef}}/tasks/{{taskId}}/time-entries/{{timeEntryId}}",
              "host": ["{{baseUrl}}"],
              "path": ["api", "projects", "{{projectRef}}", "teams", "{{teamRef}}", "tasks", "{{taskId}}", "time-entries", "{{timeEntryId}}"]
            },
            "description": "Deletes a time entry. Only the author can delete their own entries."
          }
        }
      ]
    },
    {
      "name": "Label-Task Assignment",
      "item": [
        {
          "name": "Add Label to Task",
          "request": {
            "method": "POST",
            "header": [],
            "url": {
              "raw": "{{baseUrl}}/api/projects/{{projectRef}}/labels/{{labelId}}/tasks/{{taskId}}",
              "host": ["{{baseUrl}}"],
              "path": ["api", "projects", "{{projectRef}}", "labels", "{{labelId}}", "tasks", "{{taskId}}"]
            },
            "description": "Assigns a label to a task."
          }
        },
        {
          "name": "Remove Label from Task",
          "request": {
            "method": "DELETE",
            "header": [],
            "url": {
              "raw": "{{baseUrl}}/api/projects/{{projectRef}}/labels/{{labelId}}/tasks/{{taskId}}",
              "host": ["{{baseUrl}}"],
              "path": ["api", "projects", "{{projectRef}}", "labels", "{{labelId}}", "tasks", "{{taskId}}"]
            },
            "description": "Removes a label from a task."
          }
        }
      ]
    },
    {
      "name": "Error Scenarios",
      "item": [
        {
          "name": "Create Task - Missing Title",
          "request": {
            "method": "POST",
            "header": [
              { "key": "Content-Type", "value": "application/json" }
            ],
            "body": {
              "mode": "raw",
              "raw": "{\n  \"description\": \"This should fail - no title\"\n}"
            },
            "url": {
              "raw": "{{baseUrl}}/api/projects/{{projectRef}}/teams/{{teamRef}}/tasks",
              "host": ["{{baseUrl}}"],
              "path": ["api", "projects", "{{projectRef}}", "teams", "{{teamRef}}", "tasks"]
            },
            "description": "Expects 400 — title is required."
          }
        },
        {
          "name": "Create Label - Invalid Color",
          "request": {
            "method": "POST",
            "header": [
              { "key": "Content-Type", "value": "application/json" }
            ],
            "body": {
              "mode": "raw",
              "raw": "{\n  \"name\": \"invalid-label\",\n  \"color\": \"not-a-hex-color\"\n}"
            },
            "url": {
              "raw": "{{baseUrl}}/api/projects/{{projectRef}}/labels",
              "host": ["{{baseUrl}}"],
              "path": ["api", "projects", "{{projectRef}}", "labels"]
            },
            "description": "Expects 400 — color must match hex pattern."
          }
        },
        {
          "name": "Get Non-Existent Task",
          "request": {
            "method": "GET",
            "header": [],
            "url": {
              "raw": "{{baseUrl}}/api/projects/{{projectRef}}/teams/{{teamRef}}/tasks/00000000-0000-0000-0000-000000000000",
              "host": ["{{baseUrl}}"],
              "path": ["api", "projects", "{{projectRef}}", "teams", "{{teamRef}}", "tasks", "00000000-0000-0000-0000-000000000000"]
            },
            "description": "Expects 404 — task not found."
          }
        },
        {
          "name": "Delete Without Auth",
          "request": {
            "method": "DELETE",
            "header": [],
            "url": {
              "raw": "{{baseUrl}}/api/projects/{{projectRef}}/teams/{{teamRef}}/tasks/{{taskId}}",
              "host": ["{{baseUrl}}"],
              "path": ["api", "projects", "{{projectRef}}", "teams", "{{teamRef}}", "tasks", "{{taskId}}"]
            },
            "description": "Send this without cookies/authentication. Expects 401 or 403."
          }
        }
      ]
    }
  ]
}
